embackuptest/__init__.py
embackuptest/__main__.py
embackuptest/embackuptest.py
embackuptest-0.1.1.dist-info/METADATA
embackuptest-0.1.1.dist-info/WHEEL
embackuptest-0.1.1.dist-info/top_level.txt
embackuptest-0.1.1.dist-info/RECORD
