Metadata-Version: 2.1
Name: embackuptest
Version: 0.1.1
Summary: Experimental package for RDS backup
Home-page: https://github.com/emiksa/backup-script
Author: Ernestas Miksa
Author-email: kinkan@yandex.com
License: UNKNOWN
Platform: UNKNOWN
Requires-Dist: boto3
Requires-Dist: click
